omnik/InverterMsg.py
omnik/__init__.py
omnik/datalogger.py
omnik/daylight.py
omnik/ha_logger.py
omnik/plant.py
omnik/dsmr/__init__.py
omnik/dsmr/terminal.py
omnik/plugin_client/__init__.py
omnik/plugin_client/localproxy.py
omnik/plugin_client/solarmanpv.py
omnik/plugin_client/tcpclient.py
omnik/plugin_localproxy/__init__.py
omnik/plugin_localproxy/hass_api.py
omnik/plugin_localproxy/mqtt_proxy.py
omnik/plugin_localproxy/tcp_proxy.py
omnik/plugin_output/__init__.py
omnik/plugin_output/csvoutput.py
omnik/plugin_output/influxdb.py
omnik/plugin_output/mqtt.py
omnik/plugin_output/pvoutput.py
omnikdatalogger-1.15.7.data/data/share/omnikdatalogger/data_fields.json
omnikdatalogger-1.15.7.data/data/share/omnikdatalogger/omnikdatalogger.service
omnikdatalogger-1.15.7.data/scripts/omniklogger.py
omnikdatalogger-1.15.7.dist-info/licenses/LICENSE.txt
omnikdatalogger-1.15.7.dist-info/METADATA
omnikdatalogger-1.15.7.dist-info/WHEEL
omnikdatalogger-1.15.7.dist-info/top_level.txt
omnikdatalogger-1.15.7.dist-info/RECORD
