Metadata-Version: 2.4
Name: omnikdatalogger
Version: 1.15.7
Summary: Omnik Data Logger
Home-page: https://github.com/jbouwh/omnikdatalogger
Author: Jan Bouwhuis
Author-email: jan@jbsoft.nl
License: gpl-3.0
Classifier: Development Status :: 5 - Production/Stable
Classifier: Topic :: Home Automation
Classifier: Programming Language :: Python :: 3.7
Classifier: License :: OSI Approved :: GNU General Public License v3 (GPLv3)
Classifier: Operating System :: OS Independent
License-File: LICENSE.txt
Requires-Dist: configparser>=3.7.4
Requires-Dist: requests>=2.21.0
Requires-Dist: cachetools>=3.1.1
Requires-Dist: pytz>=2019.1
Requires-Dist: paho-mqtt>=1.6.1
Requires-Dist: dsmr-parser>=1.3.2
Requires-Dist: astral>=1.10.1
Requires-Dist: pyyaml>=5.1
Requires-Dist: influxdb-client>=1.26
Dynamic: author
Dynamic: author-email
Dynamic: classifier
Dynamic: description
Dynamic: description-content-type
Dynamic: home-page
Dynamic: license
Dynamic: license-file
Dynamic: requires-dist
Dynamic: summary
